{
  "meta": {
    "created_date": "2021-07-04T21:23:15",
    "updated_date": "2021-11-12T22:06:38",
    "field_reference": "https://developer.wordpress.org/rest-api/reference/pages/",
    "api_version": "v2",
    "api_url": "https://live-drought-ca-gov.pantheonsite.io/wp-json/wp/v2/",
    "process": {
      "source_code": "https://github.com/cagov/wordpress-to-github",
      "source_data": "https://live-drought-ca-gov.pantheonsite.io",
      "deployment_target": "https://github.com/cagov/drought.ca.gov/tree/main"
    },
    "refresh_frequency": "as needed"
  },
  "data": {
    "id": 24,
    "date": "2021-07-04T14:23:15",
    "date_gmt": "2021-07-04T21:23:15",
    "guid": "https://live-drought-ca-gov.pantheonsite.io/?page_id=24",
    "modified": "2021-11-12T14:06:38",
    "modified_gmt": "2021-11-12T22:06:38",
    "slug": "homepage",
    "status": "publish",
    "type": "page",
    "link": "https://live-drought-ca-gov.pantheonsite.io/",
    "title": "California drought action",
    "excerpt": "<p>Are we still in a drought? Despite the recent welcome rain, the answer is yes. Experts say that it would take 140% of the state’s normal yearly rainfall to recover from drought. Find out more in our weekly California Drought Update. Read weekly update State actions against drought News</p>\n",
    "author": "Peggy Gartin",
    "featured_media": 0,
    "parent": 0,
    "menu_order": 0,
    "comment_status": "closed",
    "ping_status": "closed",
    "template": "landing",
    "meta": [],
    "categories": [],
    "tags": [
      "homepage",
      "launch content"
    ],
    "design_system_fields": {
      "template": "landing"
    },
    "og_meta": {
      "editor": {
        "platform": "WordPress",
        "plugin": "autodescription",
        "plugin_name": "The SEO Framework",
        "plugin_version": "4.1.5.1",
        "editor_url": "https://live-drought-ca-gov.pantheonsite.io"
      },
      "site_name": "California drought action",
      "site_description": "Learn more about current conditions, the state’s response and informational resources available to the public.",
      "site_url": "https://live-drought-ca-gov.pantheonsite.io",
      "canonical_url": "https://live-drought-ca-gov.pantheonsite.io/",
      "page_title": "California drought action",
      "page_description": "Learn more about current conditions, the state’s response and informational resources available to the public.",
      "page_social_image_url": "https://live-drought-ca-gov.pantheonsite.io/wp-content/uploads/2021/09/cropped-drought-photo.png",
      "page_social_image_width": 1200,
      "page_social_image_height": 630,
      "page_social_image_alt": "",
      "meta_title": "California drought action",
      "meta_description": "Learn more about current drought conditions, the state’s drought response, and how everyone can save water.",
      "meta_canonical_url": "https://live-drought-ca-gov.pantheonsite.io/",
      "open_graph_title": "California drought action",
      "open_graph_description": "Learn more about current drought conditions, the state’s drought response, and how everyone can save water.",
      "twitter_title": "California drought action",
      "twitter_description": "Learn more about current drought conditions, the state’s drought response, and how everyone can save water."
    },
    "headless_categories": [],
    "headless_tags": [
      {
        "term_id": 16,
        "name": "homepage",
        "slug": "homepage",
        "term_group": 0,
        "term_taxonomy_id": 16,
        "taxonomy": "post_tag",
        "description": "",
        "parent": 0,
        "filter": "raw"
      },
      {
        "term_id": 15,
        "name": "launch content",
        "slug": "launch-content",
        "term_group": 0,
        "term_taxonomy_id": 15,
        "taxonomy": "post_tag",
        "description": "",
        "parent": 0,
        "filter": "raw"
      }
    ],
    "headless_publishing": [],
    "headless_preview": [],
    "wordpress_url": "https://live-drought-ca-gov.pantheonsite.io/"
  }
}