{
  "meta": {
    "created_date": "2019-04-12T22:24:00",
    "updated_date": "2021-07-01T17:52:26",
    "field_reference": "https://developer.wordpress.org/rest-api/reference/posts/",
    "api_version": "v2",
    "api_url": "https://cannabis.ca.gov/wp-json/wp/v2/",
    "process": {
      "source_code": "https://github.com/cagov/wordpress-to-github",
      "source_data": "https://cannabis.ca.gov",
      "deployment_target": "https://github.com/cagov/cannabis.ca.gov/tree/development"
    },
    "refresh_frequency": "as needed"
  },
  "data": {
    "id": 6207,
    "date": "2019-04-12T22:24:00",
    "date_gmt": "2019-04-12T22:24:00",
    "guid": "http://wordpress.test:8888/content-types/announcement/state-agencies-host-four-cannabis-permitting-workshops-in-may-and-june/",
    "modified": "2021-07-01T10:52:26",
    "modified_gmt": "2021-07-01T17:52:26",
    "slug": "state-agencies-host-four-cannabis-permitting-workshops-in-may-and-june",
    "status": "publish",
    "type": "post",
    "link": "https://cannabis.ca.gov/2019/04/12/state-agencies-host-four-cannabis-permitting-workshops-in-may-and-june/",
    "title": "State Agencies Host Four Cannabis Permitting Workshops in May and June",
    "excerpt": "<p>The California Department of Fish and Wildlife (CDFW), the California Department of Food and Agriculture (CDFA) and the State Water Resources Control Board (SWRCB) are hosting several cannabis permitting workshops in May and June.</p>\n",
    "author": "Department of Cannabis Control",
    "featured_media": 0,
    "comment_status": "closed",
    "ping_status": "closed",
    "sticky": false,
    "template": "/www/wp-content/plugins/ca-design-system-gutenberg-blocks/includes/templates/template-single-press-release.php",
    "format": "standard",
    "meta": {
      "_et_pb_use_builder": "",
      "_et_pb_old_content": "",
      "_et_gb_content_width": ""
    },
    "categories": [
      "Announcements"
    ],
    "tags": [
      "California",
      "California cannabis",
      "California department of fish and wildlife",
      "California Department of Food and Agriculture",
      "Cannabis",
      "Cultivation",
      "June",
      "Licensing",
      "May",
      "Overview",
      "Permitting",
      "Presentations",
      "Program",
      "Questions",
      "Staff",
      "State Water Boards",
      "Workshop"
    ],
    "design_system_fields": {
      "display_title": false
    },
    "wordpress_url": "https://cannabis.ca.gov/2019/04/12/state-agencies-host-four-cannabis-permitting-workshops-in-may-and-june/"
  }
}