{
  "term_id": 777,
  "name": "Header Menu",
  "slug": "header-menu",
  "term_group": 0,
  "term_taxonomy_id": 777,
  "taxonomy": "nav_menu",
  "description": "",
  "parent": 0,
  "count": 42,
  "filter": "raw",
  "items": [
    {
      "ID": 9890,
      "post_author": "1",
      "post_date": "2022-03-30 19:21:29",
      "post_date_gmt": "2022-03-29 05:23:28",
      "post_content": " ",
      "post_title": "",
      "post_excerpt": "",
      "post_status": "publish",
      "comment_status": "closed",
      "ping_status": "closed",
      "post_password": "",
      "post_name": "9890",
      "to_ping": "",
      "pinged": "",
      "post_modified": "2022-03-30 19:21:29",
      "post_modified_gmt": "2022-03-31 02:21:29",
      "post_content_filtered": "",
      "post_parent": 0,
      "guid": "https://api.cannabis.ca.gov/2022/03/28/9890/",
      "menu_order": 1,
      "post_type": "nav_menu_item",
      "post_mime_type": "",
      "comment_count": "0",
      "filter": "raw",
      "db_id": 9890,
      "menu_item_parent": "0",
      "object_id": "756",
      "object": "page",
      "type": "post_type",
      "type_label": "Page",
      "url": "https://api.cannabis.ca.gov/applicants/",
      "title": "Applicants",
      "target": "",
      "attr_title": "",
      "description": "",
      "classes": [
        ""
      ],
      "xfn": "",
      "slug": "applicants",
      "child_items": [
        {
          "ID": 9905,
          "post_author": "1",
          "post_date": "2022-03-30 19:21:29",
          "post_date_gmt": "2022-03-29 05:23:28",
          "post_content": " ",
          "post_title": "",
          "post_excerpt": "",
          "post_status": "publish",
          "comment_status": "closed",
          "ping_status": "closed",
          "post_password": "",
          "post_name": "9905",
          "to_ping": "",
          "pinged": "",
          "post_modified": "2022-03-30 19:21:29",
          "post_modified_gmt": "2022-03-31 02:21:29",
          "post_content_filtered": "",
          "post_parent": 756,
          "guid": "https://api.cannabis.ca.gov/2022/03/28/9905/",
          "menu_order": 2,
          "post_type": "nav_menu_item",
          "post_mime_type": "",
          "comment_count": "0",
          "filter": "raw",
          "db_id": 9905,
          "menu_item_parent": "9890",
          "object_id": "7783",
          "object": "page",
          "type": "post_type",
          "type_label": "Page",
          "url": "https://api.cannabis.ca.gov/applicants/how-to-apply-renew/",
          "title": "How to apply for or renew a license",
          "target": "",
          "attr_title": "",
          "description": "",
          "classes": [
            ""
          ],
          "xfn": "",
          "slug": "how-to-apply-renew"
        },
        {
          "ID": 9895,
          "post_author": "1",
          "post_date": "2022-03-30 19:21:29",
          "post_date_gmt": "2022-03-29 05:23:28",
          "post_content": " ",
          "post_title": "",
          "post_excerpt": "",
          "post_status": "publish",
          "comment_status": "closed",
          "ping_status": "closed",
          "post_password": "",
          "post_name": "9895",
          "to_ping": "",
          "pinged": "",
          "post_modified": "2022-03-30 19:21:29",
          "post_modified_gmt": "2022-03-31 02:21:29",
          "post_content_filtered": "",
          "post_parent": 756,
          "guid": "https://api.cannabis.ca.gov/2022/03/28/9895/",
          "menu_order": 3,
          "post_type": "nav_menu_item",
          "post_mime_type": "",
          "comment_count": "0",
          "filter": "raw",
          "db_id": 9895,
          "menu_item_parent": "9890",
          "object_id": "719",
          "object": "page",
          "type": "post_type",
          "type_label": "Page",
          "url": "https://api.cannabis.ca.gov/applicants/license-types/",
          "title": "License types",
          "target": "",
          "attr_title": "",
          "description": "",
          "classes": [
            ""
          ],
          "xfn": "",
          "slug": "license-types"
        },
        {
          "ID": 9893,
          "post_author": "1",
          "post_date": "2022-03-30 19:21:29",
          "post_date_gmt": "2022-03-29 05:23:28",
          "post_content": " ",
          "post_title": "",
          "post_excerpt": "",
          "post_status": "publish",
          "comment_status": "closed",
          "ping_status": "closed",
          "post_password": "",
          "post_name": "9893",
          "to_ping": "",
          "pinged": "",
          "post_modified": "2022-03-30 19:21:29",
          "post_modified_gmt": "2022-03-31 02:21:29",
          "post_content_filtered": "",
          "post_parent": 756,
          "guid": "https://api.cannabis.ca.gov/2022/03/28/9893/",
          "menu_order": 4,
          "post_type": "nav_menu_item",
          "post_mime_type": "",
          "comment_count": "0",
          "filter": "raw",
          "db_id": 9893,
          "menu_item_parent": "9890",
          "object_id": "721",
          "object": "page",
          "type": "post_type",
          "type_label": "Page",
          "url": "https://api.cannabis.ca.gov/applicants/application-license-fees/",
          "title": "Application and license fees",
          "target": "",
          "attr_title": "",
          "description": "",
          "classes": [
            ""
          ],
          "xfn": "",
          "slug": "application-license-fees"
        },
        {
          "ID": 9906,
          "post_author": "1",
          "post_date": "2022-03-30 19:21:29",
          "post_date_gmt": "2022-03-29 05:23:29",
          "post_content": " ",
          "post_title": "",
          "post_excerpt": "",
          "post_status": "publish",
          "comment_status": "closed",
          "ping_status": "closed",
          "post_password": "",
          "post_name": "9906",
          "to_ping": "",
          "pinged": "",
          "post_modified": "2022-03-30 19:21:29",
          "post_modified_gmt": "2022-03-31 02:21:29",
          "post_content_filtered": "",
          "post_parent": 756,
          "guid": "https://api.cannabis.ca.gov/2022/03/28/9906/",
          "menu_order": 5,
          "post_type": "nav_menu_item",
          "post_mime_type": "",
          "comment_count": "0",
          "filter": "raw",
          "db_id": 9906,
          "menu_item_parent": "9890",
          "object_id": "9249",
          "object": "page",
          "type": "post_type",
          "type_label": "Page",
          "url": "https://api.cannabis.ca.gov/applicants/equity-fee-waivers/",
          "title": "Equity fee waivers",
          "target": "",
          "attr_title": "",
          "description": "",
          "classes": [
            ""
          ],
          "xfn": "",
          "slug": "equity-fee-waivers"
        },
        {
          "ID": 9894,
          "post_author": "1",
          "post_date": "2022-03-30 19:21:29",
          "post_date_gmt": "2022-03-29 05:23:28",
          "post_content": " ",
          "post_title": "",
          "post_excerpt": "",
          "post_status": "publish",
          "comment_status": "closed",
          "ping_status": "closed",
          "post_password": "",
          "post_name": "9894",
          "to_ping": "",
          "pinged": "",
          "post_modified": "2022-03-30 19:21:29",
          "post_modified_gmt": "2022-03-31 02:21:29",
          "post_content_filtered": "",
          "post_parent": 756,
          "guid": "https://api.cannabis.ca.gov/2022/03/28/9894/",
          "menu_order": 6,
          "post_type": "nav_menu_item",
          "post_mime_type": "",
          "comment_count": "0",
          "filter": "raw",
          "db_id": 9894,
          "menu_item_parent": "9890",
          "object_id": "698",
          "object": "page",
          "type": "post_type",
          "type_label": "Page",
          "url": "https://api.cannabis.ca.gov/applicants/application-resources/",
          "title": "Application resources",
          "target": "",
          "attr_title": "",
          "description": "",
          "classes": [
            ""
          ],
          "xfn": "",
          "slug": "application-resources"
        },
        {
          "ID": 9896,
          "post_author": "1",
          "post_date": "2022-03-30 19:21:29",
          "post_date_gmt": "2022-03-29 05:23:28",
          "post_content": " ",
          "post_title": "",
          "post_excerpt": "",
          "post_status": "publish",
          "comment_status": "closed",
          "ping_status": "closed",
          "post_password": "",
          "post_name": "9896",
          "to_ping": "",
          "pinged": "",
          "post_modified": "2022-03-30 19:21:29",
          "post_modified_gmt": "2022-03-31 02:21:29",
          "post_content_filtered": "",
          "post_parent": 756,
          "guid": "https://api.cannabis.ca.gov/2022/03/28/9896/",
          "menu_order": 7,
          "post_type": "nav_menu_item",
          "post_mime_type": "",
          "comment_count": "0",
          "filter": "raw",
          "db_id": 9896,
          "menu_item_parent": "9890",
          "object_id": "715",
          "object": "page",
          "type": "post_type",
          "type_label": "Page",
          "url": "https://api.cannabis.ca.gov/applicants/access-license-portals/",
          "title": "Access the license portals",
          "target": "",
          "attr_title": "",
          "description": "",
          "classes": [
            ""
          ],
          "xfn": "",
          "slug": "access-license-portals"
        }
      ]
    },
    {
      "ID": 9892,
      "post_author": "1",
      "post_date": "2022-03-30 19:21:29",
      "post_date_gmt": "2022-03-29 05:23:28",
      "post_content": " ",
      "post_title": "",
      "post_excerpt": "",
      "post_status": "publish",
      "comment_status": "closed",
      "ping_status": "closed",
      "post_password": "",
      "post_name": "9892",
      "to_ping": "",
      "pinged": "",
      "post_modified": "2022-03-30 19:21:29",
      "post_modified_gmt": "2022-03-31 02:21:29",
      "post_content_filtered": "",
      "post_parent": 0,
      "guid": "https://api.cannabis.ca.gov/2022/03/28/9892/",
      "menu_order": 8,
      "post_type": "nav_menu_item",
      "post_mime_type": "",
      "comment_count": "0",
      "filter": "raw",
      "db_id": 9892,
      "menu_item_parent": "0",
      "object_id": "758",
      "object": "page",
      "type": "post_type",
      "type_label": "Page",
      "url": "https://api.cannabis.ca.gov/licensees/",
      "title": "Licensees",
      "target": "",
      "attr_title": "",
      "description": "",
      "classes": [
        ""
      ],
      "xfn": "",
      "slug": "licensees",
      "child_items": [
        {
          "ID": 9898,
          "post_author": "1",
          "post_date": "2022-03-30 19:21:29",
          "post_date_gmt": "2022-03-29 05:23:28",
          "post_content": " ",
          "post_title": "",
          "post_excerpt": "",
          "post_status": "publish",
          "comment_status": "closed",
          "ping_status": "closed",
          "post_password": "",
          "post_name": "9898",
          "to_ping": "",
          "pinged": "",
          "post_modified": "2022-03-30 19:21:29",
          "post_modified_gmt": "2022-03-31 02:21:29",
          "post_content_filtered": "",
          "post_parent": 758,
          "guid": "https://api.cannabis.ca.gov/2022/03/28/9898/",
          "menu_order": 9,
          "post_type": "nav_menu_item",
          "post_mime_type": "",
          "comment_count": "0",
          "filter": "raw",
          "db_id": 9898,
          "menu_item_parent": "9892",
          "object_id": "718",
          "object": "page",
          "type": "post_type",
          "type_label": "Page",
          "url": "https://api.cannabis.ca.gov/licensees/cultivation/",
          "title": "Cultivation",
          "target": "",
          "attr_title": "",
          "description": "",
          "classes": [
            ""
          ],
          "xfn": "",
          "slug": "cultivation"
        },
        {
          "ID": 9901,
          "post_author": "1",
          "post_date": "2022-03-30 19:21:30",
          "post_date_gmt": "2022-03-29 05:23:28",
          "post_content": " ",
          "post_title": "",
          "post_excerpt": "",
          "post_status": "publish",
          "comment_status": "closed",
          "ping_status": "closed",
          "post_password": "",
          "post_name": "9901",
          "to_ping": "",
          "pinged": "",
          "post_modified": "2022-03-30 19:21:30",
          "post_modified_gmt": "2022-03-31 02:21:30",
          "post_content_filtered": "",
          "post_parent": 758,
          "guid": "https://api.cannabis.ca.gov/2022/03/28/9901/",
          "menu_order": 10,
          "post_type": "nav_menu_item",
          "post_mime_type": "",
          "comment_count": "0",
          "filter": "raw",
          "db_id": 9901,
          "menu_item_parent": "9892",
          "object_id": "717",
          "object": "page",
          "type": "post_type",
          "type_label": "Page",
          "url": "https://api.cannabis.ca.gov/licensees/manufacturing/",
          "title": "Manufacturing",
          "target": "",
          "attr_title": "",
          "description": "",
          "classes": [
            ""
          ],
          "xfn": "",
          "slug": "manufacturing"
        },
        {
          "ID": 9899,
          "post_author": "1",
          "post_date": "2022-03-30 19:21:30",
          "post_date_gmt": "2022-03-29 05:23:28",
          "post_content": " ",
          "post_title": "",
          "post_excerpt": "",
          "post_status": "publish",
          "comment_status": "closed",
          "ping_status": "closed",
          "post_password": "",
          "post_name": "9899",
          "to_ping": "",
          "pinged": "",
          "post_modified": "2022-03-30 19:21:30",
          "post_modified_gmt": "2022-03-31 02:21:30",
          "post_content_filtered": "",
          "post_parent": 758,
          "guid": "https://api.cannabis.ca.gov/2022/03/28/9899/",
          "menu_order": 11,
          "post_type": "nav_menu_item",
          "post_mime_type": "",
          "comment_count": "0",
          "filter": "raw",
          "db_id": 9899,
          "menu_item_parent": "9892",
          "object_id": "699",
          "object": "page",
          "type": "post_type",
          "type_label": "Page",
          "url": "https://api.cannabis.ca.gov/licensees/distribution/",
          "title": "Distribution",
          "target": "",
          "attr_title": "",
          "description": "",
          "classes": [
            ""
          ],
          "xfn": "",
          "slug": "distribution"
        },
        {
          "ID": 9903,
          "post_author": "1",
          "post_date": "2022-03-30 19:21:30",
          "post_date_gmt": "2022-03-29 05:23:28",
          "post_content": " ",
          "post_title": "",
          "post_excerpt": "",
          "post_status": "publish",
          "comment_status": "closed",
          "ping_status": "closed",
          "post_password": "",
          "post_name": "9903",
          "to_ping": "",
          "pinged": "",
          "post_modified": "2022-03-30 19:21:30",
          "post_modified_gmt": "2022-03-31 02:21:30",
          "post_content_filtered": "",
          "post_parent": 758,
          "guid": "https://api.cannabis.ca.gov/2022/03/28/9903/",
          "menu_order": 12,
          "post_type": "nav_menu_item",
          "post_mime_type": "",
          "comment_count": "0",
          "filter": "raw",
          "db_id": 9903,
          "menu_item_parent": "9892",
          "object_id": "692",
          "object": "page",
          "type": "post_type",
          "type_label": "Page",
          "url": "https://api.cannabis.ca.gov/licensees/testing-laboratories/",
          "title": "Testing laboratories",
          "target": "",
          "attr_title": "",
          "description": "",
          "classes": [
            ""
          ],
          "xfn": "",
          "slug": "testing-laboratories"
        },
        {
          "ID": 9902,
          "post_author": "1",
          "post_date": "2022-03-30 19:21:30",
          "post_date_gmt": "2022-03-29 05:23:28",
          "post_content": " ",
          "post_title": "",
          "post_excerpt": "",
          "post_status": "publish",
          "comment_status": "closed",
          "ping_status": "closed",
          "post_password": "",
          "post_name": "9902",
          "to_ping": "",
          "pinged": "",
          "post_modified": "2022-03-30 19:21:30",
          "post_modified_gmt": "2022-03-31 02:21:30",
          "post_content_filtered": "",
          "post_parent": 758,
          "guid": "https://api.cannabis.ca.gov/2022/03/28/9902/",
          "menu_order": 13,
          "post_type": "nav_menu_item",
          "post_mime_type": "",
          "comment_count": "0",
          "filter": "raw",
          "db_id": 9902,
          "menu_item_parent": "9892",
          "object_id": "711",
          "object": "page",
          "type": "post_type",
          "type_label": "Page",
          "url": "https://api.cannabis.ca.gov/licensees/retail/",
          "title": "Retail",
          "target": "",
          "attr_title": "",
          "description": "",
          "classes": [
            ""
          ],
          "xfn": "",
          "slug": "retail"
        },
        {
          "ID": 9900,
          "post_author": "1",
          "post_date": "2022-03-30 19:21:30",
          "post_date_gmt": "2022-03-29 05:23:28",
          "post_content": " ",
          "post_title": "",
          "post_excerpt": "",
          "post_status": "publish",
          "comment_status": "closed",
          "ping_status": "closed",
          "post_password": "",
          "post_name": "9900",
          "to_ping": "",
          "pinged": "",
          "post_modified": "2022-03-30 19:21:30",
          "post_modified_gmt": "2022-03-31 02:21:30",
          "post_content_filtered": "",
          "post_parent": 758,
          "guid": "https://api.cannabis.ca.gov/2022/03/28/9900/",
          "menu_order": 14,
          "post_type": "nav_menu_item",
          "post_mime_type": "",
          "comment_count": "0",
          "filter": "raw",
          "db_id": 9900,
          "menu_item_parent": "9892",
          "object_id": "702",
          "object": "page",
          "type": "post_type",
          "type_label": "Page",
          "url": "https://api.cannabis.ca.gov/licensees/events/",
          "title": "Events",
          "target": "",
          "attr_title": "",
          "description": "",
          "classes": [
            ""
          ],
          "xfn": "",
          "slug": "events"
        },
        {
          "ID": 9907,
          "post_author": "1",
          "post_date": "2022-03-30 19:21:30",
          "post_date_gmt": "2022-03-29 05:23:29",
          "post_content": " ",
          "post_title": "",
          "post_excerpt": "",
          "post_status": "publish",
          "comment_status": "closed",
          "ping_status": "closed",
          "post_password": "",
          "post_name": "9907",
          "to_ping": "",
          "pinged": "",
          "post_modified": "2022-03-30 19:21:30",
          "post_modified_gmt": "2022-03-31 02:21:30",
          "post_content_filtered": "",
          "post_parent": 758,
          "guid": "https://api.cannabis.ca.gov/2022/03/28/9907/",
          "menu_order": 15,
          "post_type": "nav_menu_item",
          "post_mime_type": "",
          "comment_count": "0",
          "filter": "raw",
          "db_id": 9907,
          "menu_item_parent": "9892",
          "object_id": "9492",
          "object": "page",
          "type": "post_type",
          "type_label": "Page",
          "url": "https://api.cannabis.ca.gov/licensees/cannaconnect-compliance-hub/",
          "title": "CannaConnect Compliance Hub",
          "target": "",
          "attr_title": "",
          "description": "",
          "classes": [
            ""
          ],
          "xfn": "",
          "slug": "cannaconnect-compliance-hub"
        }
      ]
    },
    {
      "ID": 9891,
      "post_author": "1",
      "post_date": "2022-03-30 19:21:30",
      "post_date_gmt": "2022-03-29 05:23:28",
      "post_content": " ",
      "post_title": "",
      "post_excerpt": "",
      "post_status": "publish",
      "comment_status": "closed",
      "ping_status": "closed",
      "post_password": "",
      "post_name": "9891",
      "to_ping": "",
      "pinged": "",
      "post_modified": "2022-03-30 19:21:30",
      "post_modified_gmt": "2022-03-31 02:21:30",
      "post_content_filtered": "",
      "post_parent": 0,
      "guid": "https://api.cannabis.ca.gov/2022/03/28/9891/",
      "menu_order": 16,
      "post_type": "nav_menu_item",
      "post_mime_type": "",
      "comment_count": "0",
      "filter": "raw",
      "db_id": 9891,
      "menu_item_parent": "0",
      "object_id": "757",
      "object": "page",
      "type": "post_type",
      "type_label": "Page",
      "url": "https://api.cannabis.ca.gov/consumers/",
      "title": "Consumers",
      "target": "",
      "attr_title": "",
      "description": "",
      "classes": [
        ""
      ],
      "xfn": "",
      "slug": "consumers",
      "child_items": [
        {
          "ID": 9897,
          "post_author": "1",
          "post_date": "2022-03-30 19:21:30",
          "post_date_gmt": "2022-03-29 05:23:28",
          "post_content": "",
          "post_title": "What’s legal",
          "post_excerpt": "",
          "post_status": "publish",
          "comment_status": "closed",
          "ping_status": "closed",
          "post_password": "",
          "post_name": "whats-legal",
          "to_ping": "",
          "pinged": "",
          "post_modified": "2022-03-30 19:21:30",
          "post_modified_gmt": "2022-03-31 02:21:30",
          "post_content_filtered": "",
          "post_parent": 757,
          "guid": "https://api.cannabis.ca.gov/2022/03/28/whats-legal/",
          "menu_order": 17,
          "post_type": "nav_menu_item",
          "post_mime_type": "",
          "comment_count": "0",
          "filter": "raw",
          "db_id": 9897,
          "menu_item_parent": "9891",
          "object_id": "704",
          "object": "page",
          "type": "post_type",
          "type_label": "Page",
          "url": "https://api.cannabis.ca.gov/consumers/whats-legal/",
          "title": "What’s legal",
          "target": "",
          "attr_title": "",
          "description": "",
          "classes": [
            ""
          ],
          "xfn": "",
          "slug": "whats-legal"
        },
        {
          "ID": 9911,
          "post_author": "1",
          "post_date": "2022-03-30 19:21:30",
          "post_date_gmt": "2022-03-29 05:23:29",
          "post_content": " ",
          "post_title": "",
          "post_excerpt": "",
          "post_status": "publish",
          "comment_status": "closed",
          "ping_status": "closed",
          "post_password": "",
          "post_name": "9911",
          "to_ping": "",
          "pinged": "",
          "post_modified": "2022-03-30 19:21:30",
          "post_modified_gmt": "2022-03-31 02:21:30",
          "post_content_filtered": "",
          "post_parent": 757,
          "guid": "https://api.cannabis.ca.gov/2022/03/28/9911/",
          "menu_order": 18,
          "post_type": "nav_menu_item",
          "post_mime_type": "",
          "comment_count": "0",
          "filter": "raw",
          "db_id": 9911,
          "menu_item_parent": "9891",
          "object_id": "695",
          "object": "page",
          "type": "post_type",
          "type_label": "Page",
          "url": "https://api.cannabis.ca.gov/consumers/medicinal-cannabis/",
          "title": "Medicinal cannabis",
          "target": "",
          "attr_title": "",
          "description": "",
          "classes": [
            ""
          ],
          "xfn": "",
          "slug": "medicinal-cannabis"
        },
        {
          "ID": 9912,
          "post_author": "1",
          "post_date": "2022-03-30 19:21:30",
          "post_date_gmt": "2022-03-29 05:23:29",
          "post_content": " ",
          "post_title": "",
          "post_excerpt": "",
          "post_status": "publish",
          "comment_status": "closed",
          "ping_status": "closed",
          "post_password": "",
          "post_name": "9912",
          "to_ping": "",
          "pinged": "",
          "post_modified": "2022-03-30 19:21:30",
          "post_modified_gmt": "2022-03-31 02:21:30",
          "post_content_filtered": "",
          "post_parent": 757,
          "guid": "https://api.cannabis.ca.gov/2022/03/28/9912/",
          "menu_order": 19,
          "post_type": "nav_menu_item",
          "post_mime_type": "",
          "comment_count": "0",
          "filter": "raw",
          "db_id": 9912,
          "menu_item_parent": "9891",
          "object_id": "705",
          "object": "page",
          "type": "post_type",
          "type_label": "Page",
          "url": "https://api.cannabis.ca.gov/consumers/responsible-cannabis-use/",
          "title": "Responsible cannabis use",
          "target": "",
          "attr_title": "",
          "description": "",
          "classes": [
            ""
          ],
          "xfn": "",
          "slug": "responsible-cannabis-use"
        },
        {
          "ID": 9913,
          "post_author": "1",
          "post_date": "2022-03-30 19:21:30",
          "post_date_gmt": "2022-03-29 05:23:29",
          "post_content": " ",
          "post_title": "",
          "post_excerpt": "",
          "post_status": "publish",
          "comment_status": "closed",
          "ping_status": "closed",
          "post_password": "",
          "post_name": "9913",
          "to_ping": "",
          "pinged": "",
          "post_modified": "2022-03-30 19:21:30",
          "post_modified_gmt": "2022-03-31 02:21:30",
          "post_content_filtered": "",
          "post_parent": 757,
          "guid": "https://api.cannabis.ca.gov/2022/03/28/9913/",
          "menu_order": 20,
          "post_type": "nav_menu_item",
          "post_mime_type": "",
          "comment_count": "0",
          "filter": "raw",
          "db_id": 9913,
          "menu_item_parent": "9891",
          "object_id": "697",
          "object": "page",
          "type": "post_type",
          "type_label": "Page",
          "url": "https://api.cannabis.ca.gov/consumers/talking-young-people-about-cannabis/",
          "title": "Talking to young people about cannabis",
          "target": "",
          "attr_title": "",
          "description": "",
          "classes": [
            ""
          ],
          "xfn": "",
          "slug": "talking-young-people-about-cannabis"
        }
      ]
    },
    {
      "ID": 9923,
      "post_author": "1",
      "post_date": "2022-03-30 19:21:30",
      "post_date_gmt": "2022-03-29 05:23:30",
      "post_content": " ",
      "post_title": "",
      "post_excerpt": "",
      "post_status": "publish",
      "comment_status": "closed",
      "ping_status": "closed",
      "post_password": "",
      "post_name": "9923",
      "to_ping": "",
      "pinged": "",
      "post_modified": "2022-03-30 19:21:30",
      "post_modified_gmt": "2022-03-31 02:21:30",
      "post_content_filtered": "",
      "post_parent": 0,
      "guid": "https://api.cannabis.ca.gov/2022/03/28/9923/",
      "menu_order": 21,
      "post_type": "nav_menu_item",
      "post_mime_type": "",
      "comment_count": "0",
      "filter": "raw",
      "db_id": 9923,
      "menu_item_parent": "0",
      "object_id": "9438",
      "object": "page",
      "type": "post_type",
      "type_label": "Page",
      "url": "https://api.cannabis.ca.gov/cannabis-laws/",
      "title": "Cannabis laws",
      "target": "",
      "attr_title": "",
      "description": "",
      "classes": [
        ""
      ],
      "xfn": "",
      "slug": "cannabis-laws",
      "child_items": [
        {
          "ID": 9916,
          "post_author": "1",
          "post_date": "2022-03-30 19:21:30",
          "post_date_gmt": "2022-03-29 05:23:29",
          "post_content": "",
          "post_title": "California’s cannabis laws",
          "post_excerpt": "",
          "post_status": "publish",
          "comment_status": "closed",
          "ping_status": "closed",
          "post_password": "",
          "post_name": "californias-cannabis-laws",
          "to_ping": "",
          "pinged": "",
          "post_modified": "2022-03-30 19:21:30",
          "post_modified_gmt": "2022-03-31 02:21:30",
          "post_content_filtered": "",
          "post_parent": 759,
          "guid": "https://api.cannabis.ca.gov/2022/03/28/californias-cannabis-laws/",
          "menu_order": 22,
          "post_type": "nav_menu_item",
          "post_mime_type": "",
          "comment_count": "0",
          "filter": "raw",
          "db_id": 9916,
          "menu_item_parent": "9923",
          "object_id": "713",
          "object": "page",
          "type": "post_type",
          "type_label": "Page",
          "url": "https://api.cannabis.ca.gov/resources/laws-and-regulations/",
          "title": "California’s cannabis laws",
          "target": "",
          "attr_title": "",
          "description": "",
          "classes": [
            ""
          ],
          "xfn": "",
          "slug": "laws-and-regulations"
        },
        {
          "ID": 10288,
          "post_author": "1",
          "post_date": "2022-03-30 19:21:30",
          "post_date_gmt": "2022-03-29 20:14:14",
          "post_content": " ",
          "post_title": "",
          "post_excerpt": "",
          "post_status": "publish",
          "comment_status": "closed",
          "ping_status": "closed",
          "post_password": "",
          "post_name": "10288",
          "to_ping": "",
          "pinged": "",
          "post_modified": "2022-03-30 19:21:30",
          "post_modified_gmt": "2022-03-31 02:21:30",
          "post_content_filtered": "",
          "post_parent": 9438,
          "guid": "https://api.cannabis.ca.gov/?p=10288",
          "menu_order": 23,
          "post_type": "nav_menu_item",
          "post_mime_type": "",
          "comment_count": "0",
          "filter": "raw",
          "db_id": 10288,
          "menu_item_parent": "9923",
          "object_id": "10273",
          "object": "page",
          "type": "post_type",
          "type_label": "Page",
          "url": "https://api.cannabis.ca.gov/cannabis-laws/where-cannabis-business-is-legal-in-california/",
          "title": "Where cannabis business is legal in California",
          "target": "",
          "attr_title": "",
          "description": "",
          "classes": [
            ""
          ],
          "xfn": "",
          "slug": "where-cannabis-business-is-legal-in-california"
        },
        {
          "ID": 9926,
          "post_author": "1",
          "post_date": "2022-03-30 19:21:30",
          "post_date_gmt": "2022-03-29 05:23:30",
          "post_content": " ",
          "post_title": "",
          "post_excerpt": "",
          "post_status": "publish",
          "comment_status": "closed",
          "ping_status": "closed",
          "post_password": "",
          "post_name": "9926",
          "to_ping": "",
          "pinged": "",
          "post_modified": "2022-03-30 19:21:30",
          "post_modified_gmt": "2022-03-31 02:21:30",
          "post_content_filtered": "",
          "post_parent": 9438,
          "guid": "https://api.cannabis.ca.gov/2022/03/28/9926/",
          "menu_order": 24,
          "post_type": "nav_menu_item",
          "post_mime_type": "",
          "comment_count": "0",
          "filter": "raw",
          "db_id": 9926,
          "menu_item_parent": "9923",
          "object_id": "9437",
          "object": "page",
          "type": "post_type",
          "type_label": "Page",
          "url": "https://api.cannabis.ca.gov/cannabis-laws/dcc-regulations/",
          "title": "DCC regulations",
          "target": "",
          "attr_title": "",
          "description": "",
          "classes": [
            ""
          ],
          "xfn": "",
          "slug": "dcc-regulations"
        },
        {
          "ID": 9925,
          "post_author": "1",
          "post_date": "2022-03-30 19:21:30",
          "post_date_gmt": "2022-03-29 05:23:30",
          "post_content": " ",
          "post_title": "",
          "post_excerpt": "",
          "post_status": "publish",
          "comment_status": "closed",
          "ping_status": "closed",
          "post_password": "",
          "post_name": "9925",
          "to_ping": "",
          "pinged": "",
          "post_modified": "2022-03-30 19:21:30",
          "post_modified_gmt": "2022-03-31 02:21:30",
          "post_content_filtered": "",
          "post_parent": 9438,
          "guid": "https://api.cannabis.ca.gov/2022/03/28/9925/",
          "menu_order": 25,
          "post_type": "nav_menu_item",
          "post_mime_type": "",
          "comment_count": "0",
          "filter": "raw",
          "db_id": 9925,
          "menu_item_parent": "9923",
          "object_id": "9443",
          "object": "page",
          "type": "post_type",
          "type_label": "Page",
          "url": "https://api.cannabis.ca.gov/cannabis-laws/how-regulations-are-made/",
          "title": "How regulations are made",
          "target": "",
          "attr_title": "",
          "description": "",
          "classes": [
            ""
          ],
          "xfn": "",
          "slug": "how-regulations-are-made"
        },
        {
          "ID": 9924,
          "post_author": "1",
          "post_date": "2022-03-30 19:21:30",
          "post_date_gmt": "2022-03-29 05:23:30",
          "post_content": " ",
          "post_title": "",
          "post_excerpt": "",
          "post_status": "publish",
          "comment_status": "closed",
          "ping_status": "closed",
          "post_password": "",
          "post_name": "9924",
          "to_ping": "",
          "pinged": "",
          "post_modified": "2022-03-30 19:21:30",
          "post_modified_gmt": "2022-03-31 02:21:30",
          "post_content_filtered": "",
          "post_parent": 759,
          "guid": "https://api.cannabis.ca.gov/2022/03/28/9924/",
          "menu_order": 26,
          "post_type": "nav_menu_item",
          "post_mime_type": "",
          "comment_count": "0",
          "filter": "raw",
          "db_id": 9924,
          "menu_item_parent": "9923",
          "object_id": "710",
          "object": "page",
          "type": "post_type",
          "type_label": "Page",
          "url": "https://api.cannabis.ca.gov/resources/rulemaking/",
          "title": "Rulemaking",
          "target": "",
          "attr_title": "",
          "description": "",
          "classes": [
            ""
          ],
          "xfn": "",
          "slug": "rulemaking"
        },
        {
          "ID": 9927,
          "post_author": "1",
          "post_date": "2022-03-30 19:21:30",
          "post_date_gmt": "2022-03-29 05:23:30",
          "post_content": " ",
          "post_title": "",
          "post_excerpt": "",
          "post_status": "publish",
          "comment_status": "closed",
          "ping_status": "closed",
          "post_password": "",
          "post_name": "9927",
          "to_ping": "",
          "pinged": "",
          "post_modified": "2022-03-30 19:21:30",
          "post_modified_gmt": "2022-03-31 02:21:30",
          "post_content_filtered": "",
          "post_parent": 758,
          "guid": "https://api.cannabis.ca.gov/2022/03/28/9927/",
          "menu_order": 27,
          "post_type": "nav_menu_item",
          "post_mime_type": "",
          "comment_count": "0",
          "filter": "raw",
          "db_id": 9927,
          "menu_item_parent": "9923",
          "object_id": "9301",
          "object": "page",
          "type": "post_type",
          "type_label": "Page",
          "url": "https://api.cannabis.ca.gov/licensees/compliance-with-state-law/",
          "title": "Compliance with state law",
          "target": "",
          "attr_title": "",
          "description": "",
          "classes": [
            ""
          ],
          "xfn": "",
          "slug": "compliance-with-state-law"
        }
      ]
    },
    {
      "ID": 9909,
      "post_author": "1",
      "post_date": "2022-03-30 19:21:30",
      "post_date_gmt": "2022-03-29 05:23:29",
      "post_content": " ",
      "post_title": "",
      "post_excerpt": "",
      "post_status": "publish",
      "comment_status": "closed",
      "ping_status": "closed",
      "post_password": "",
      "post_name": "9909",
      "to_ping": "",
      "pinged": "",
      "post_modified": "2022-03-30 19:21:30",
      "post_modified_gmt": "2022-03-31 02:21:30",
      "post_content_filtered": "",
      "post_parent": 0,
      "guid": "https://api.cannabis.ca.gov/2022/03/28/9909/",
      "menu_order": 28,
      "post_type": "nav_menu_item",
      "post_mime_type": "",
      "comment_count": "0",
      "filter": "raw",
      "db_id": 9909,
      "menu_item_parent": "0",
      "object_id": "759",
      "object": "page",
      "type": "post_type",
      "type_label": "Page",
      "url": "https://api.cannabis.ca.gov/resources/",
      "title": "Resources",
      "target": "",
      "attr_title": "",
      "description": "",
      "classes": [
        ""
      ],
      "xfn": "",
      "slug": "resources",
      "child_items": [
        {
          "ID": 9922,
          "post_author": "1",
          "post_date": "2022-03-30 19:21:30",
          "post_date_gmt": "2022-03-29 05:23:29",
          "post_content": " ",
          "post_title": "",
          "post_excerpt": "",
          "post_status": "publish",
          "comment_status": "closed",
          "ping_status": "closed",
          "post_password": "",
          "post_name": "9922",
          "to_ping": "",
          "pinged": "",
          "post_modified": "2022-03-30 19:21:30",
          "post_modified_gmt": "2022-03-31 02:21:30",
          "post_content_filtered": "",
          "post_parent": 759,
          "guid": "https://api.cannabis.ca.gov/2022/03/28/9922/",
          "menu_order": 29,
          "post_type": "nav_menu_item",
          "post_mime_type": "",
          "comment_count": "0",
          "filter": "raw",
          "db_id": 9922,
          "menu_item_parent": "9909",
          "object_id": "9345",
          "object": "page",
          "type": "post_type",
          "type_label": "Page",
          "url": "https://api.cannabis.ca.gov/resources/cannabis-recalls-and-safety-notices/",
          "title": "Cannabis recalls and safety notices",
          "target": "",
          "attr_title": "",
          "description": "",
          "classes": [
            ""
          ],
          "xfn": "",
          "slug": "cannabis-recalls-and-safety-notices"
        },
        {
          "ID": 9917,
          "post_author": "1",
          "post_date": "2022-03-30 19:21:30",
          "post_date_gmt": "2022-03-29 05:23:29",
          "post_content": " ",
          "post_title": "",
          "post_excerpt": "",
          "post_status": "publish",
          "comment_status": "closed",
          "ping_status": "closed",
          "post_password": "",
          "post_name": "9917",
          "to_ping": "",
          "pinged": "",
          "post_modified": "2022-03-30 19:21:30",
          "post_modified_gmt": "2022-03-31 02:21:30",
          "post_content_filtered": "",
          "post_parent": 759,
          "guid": "https://api.cannabis.ca.gov/2022/03/28/9917/",
          "menu_order": 30,
          "post_type": "nav_menu_item",
          "post_mime_type": "",
          "comment_count": "0",
          "filter": "raw",
          "db_id": 9917,
          "menu_item_parent": "9909",
          "object_id": "688",
          "object": "page",
          "type": "post_type",
          "type_label": "Page",
          "url": "https://api.cannabis.ca.gov/resources/running-business/",
          "title": "Running a business in California",
          "target": "",
          "attr_title": "",
          "description": "",
          "classes": [
            ""
          ],
          "xfn": "",
          "slug": "running-business"
        },
        {
          "ID": 9915,
          "post_author": "1",
          "post_date": "2022-03-30 19:21:30",
          "post_date_gmt": "2022-03-29 05:23:29",
          "post_content": " ",
          "post_title": "",
          "post_excerpt": "",
          "post_status": "publish",
          "comment_status": "closed",
          "ping_status": "closed",
          "post_password": "",
          "post_name": "9915",
          "to_ping": "",
          "pinged": "",
          "post_modified": "2022-03-30 19:21:30",
          "post_modified_gmt": "2022-03-31 02:21:30",
          "post_content_filtered": "",
          "post_parent": 759,
          "guid": "https://api.cannabis.ca.gov/2022/03/28/9915/",
          "menu_order": 31,
          "post_type": "nav_menu_item",
          "post_mime_type": "",
          "comment_count": "0",
          "filter": "raw",
          "db_id": 9915,
          "menu_item_parent": "9909",
          "object_id": "712",
          "object": "page",
          "type": "post_type",
          "type_label": "Page",
          "url": "https://api.cannabis.ca.gov/resources/file-complaint/",
          "title": "File a complaint",
          "target": "",
          "attr_title": "",
          "description": "",
          "classes": [
            ""
          ],
          "xfn": "",
          "slug": "file-complaint"
        },
        {
          "ID": 9914,
          "post_author": "1",
          "post_date": "2022-03-30 19:21:30",
          "post_date_gmt": "2022-03-29 05:23:29",
          "post_content": " ",
          "post_title": "",
          "post_excerpt": "",
          "post_status": "publish",
          "comment_status": "closed",
          "ping_status": "closed",
          "post_password": "",
          "post_name": "9914",
          "to_ping": "",
          "pinged": "",
          "post_modified": "2022-03-30 19:21:30",
          "post_modified_gmt": "2022-03-31 02:21:30",
          "post_content_filtered": "",
          "post_parent": 759,
          "guid": "https://api.cannabis.ca.gov/2022/03/28/9914/",
          "menu_order": 32,
          "post_type": "nav_menu_item",
          "post_mime_type": "",
          "comment_count": "0",
          "filter": "raw",
          "db_id": 9914,
          "menu_item_parent": "9909",
          "object_id": "690",
          "object": "page",
          "type": "post_type",
          "type_label": "Page",
          "url": "https://api.cannabis.ca.gov/resources/disaster-relief-programs/",
          "title": "Disaster relief programs",
          "target": "",
          "attr_title": "",
          "description": "",
          "classes": [
            ""
          ],
          "xfn": "",
          "slug": "disaster-relief-programs"
        },
        {
          "ID": 9918,
          "post_author": "1",
          "post_date": "2022-03-30 19:21:30",
          "post_date_gmt": "2022-03-29 05:23:29",
          "post_content": " ",
          "post_title": "",
          "post_excerpt": "",
          "post_status": "publish",
          "comment_status": "closed",
          "ping_status": "closed",
          "post_password": "",
          "post_name": "9918",
          "to_ping": "",
          "pinged": "",
          "post_modified": "2022-03-30 19:21:30",
          "post_modified_gmt": "2022-03-31 02:21:30",
          "post_content_filtered": "",
          "post_parent": 759,
          "guid": "https://api.cannabis.ca.gov/2022/03/28/9918/",
          "menu_order": 33,
          "post_type": "nav_menu_item",
          "post_mime_type": "",
          "comment_count": "0",
          "filter": "raw",
          "db_id": 9918,
          "menu_item_parent": "9909",
          "object_id": "714",
          "object": "page",
          "type": "post_type",
          "type_label": "Page",
          "url": "https://api.cannabis.ca.gov/resources/search-for-licensed-business/",
          "title": "Search for a licensed business",
          "target": "",
          "attr_title": "",
          "description": "",
          "classes": [
            ""
          ],
          "xfn": "",
          "slug": "search-for-licensed-business"
        }
      ]
    },
    {
      "ID": 9921,
      "post_author": "1",
      "post_date": "2022-03-30 19:21:30",
      "post_date_gmt": "2022-03-29 05:23:29",
      "post_content": " ",
      "post_title": "",
      "post_excerpt": "",
      "post_status": "publish",
      "comment_status": "closed",
      "ping_status": "closed",
      "post_password": "",
      "post_name": "9921",
      "to_ping": "",
      "pinged": "",
      "post_modified": "2022-03-30 19:21:30",
      "post_modified_gmt": "2022-03-31 02:21:30",
      "post_content_filtered": "",
      "post_parent": 0,
      "guid": "https://api.cannabis.ca.gov/2022/03/28/9921/",
      "menu_order": 34,
      "post_type": "nav_menu_item",
      "post_mime_type": "",
      "comment_count": "0",
      "filter": "raw",
      "db_id": 9921,
      "menu_item_parent": "0",
      "object_id": "856",
      "object": "page",
      "type": "post_type",
      "type_label": "Page",
      "url": "https://api.cannabis.ca.gov/about-us/",
      "title": "About us",
      "target": "",
      "attr_title": "",
      "description": "",
      "classes": [
        ""
      ],
      "xfn": "",
      "slug": "about-us",
      "child_items": [
        {
          "ID": 9919,
          "post_author": "1",
          "post_date": "2022-03-30 19:21:30",
          "post_date_gmt": "2022-03-29 05:23:29",
          "post_content": "",
          "post_title": "About DCC",
          "post_excerpt": "",
          "post_status": "publish",
          "comment_status": "closed",
          "ping_status": "closed",
          "post_password": "",
          "post_name": "about-dcc",
          "to_ping": "",
          "pinged": "",
          "post_modified": "2022-03-30 19:21:30",
          "post_modified_gmt": "2022-03-31 02:21:30",
          "post_content_filtered": "",
          "post_parent": 856,
          "guid": "https://api.cannabis.ca.gov/2022/03/28/about-dcc/",
          "menu_order": 35,
          "post_type": "nav_menu_item",
          "post_mime_type": "",
          "comment_count": "0",
          "filter": "raw",
          "db_id": 9919,
          "menu_item_parent": "9921",
          "object_id": "707",
          "object": "page",
          "type": "post_type",
          "type_label": "Page",
          "url": "https://api.cannabis.ca.gov/about-us/about-dcc/",
          "title": "About DCC",
          "target": "",
          "attr_title": "",
          "description": "",
          "classes": [
            ""
          ],
          "xfn": "",
          "slug": "about-dcc"
        },
        {
          "ID": 9908,
          "post_author": "1",
          "post_date": "2022-03-30 19:21:30",
          "post_date_gmt": "2022-03-29 05:23:29",
          "post_content": " ",
          "post_title": "",
          "post_excerpt": "",
          "post_status": "publish",
          "comment_status": "closed",
          "ping_status": "closed",
          "post_password": "",
          "post_name": "9908",
          "to_ping": "",
          "pinged": "",
          "post_modified": "2022-03-30 19:21:30",
          "post_modified_gmt": "2022-03-31 02:21:30",
          "post_content_filtered": "",
          "post_parent": 856,
          "guid": "https://api.cannabis.ca.gov/2022/03/28/9908/",
          "menu_order": 36,
          "post_type": "nav_menu_item",
          "post_mime_type": "",
          "comment_count": "0",
          "filter": "raw",
          "db_id": 9908,
          "menu_item_parent": "9921",
          "object_id": "7429",
          "object": "page",
          "type": "post_type",
          "type_label": "Page",
          "url": "https://api.cannabis.ca.gov/about-us/announcements/",
          "title": "Announcements",
          "target": "",
          "attr_title": "",
          "description": "",
          "classes": [
            ""
          ],
          "xfn": "",
          "slug": "announcements"
        },
        {
          "ID": 9920,
          "post_author": "1",
          "post_date": "2022-03-30 19:21:30",
          "post_date_gmt": "2022-03-29 05:23:29",
          "post_content": "",
          "post_title": "DCC events",
          "post_excerpt": "",
          "post_status": "publish",
          "comment_status": "closed",
          "ping_status": "closed",
          "post_password": "",
          "post_name": "dcc-events",
          "to_ping": "",
          "pinged": "",
          "post_modified": "2022-03-30 19:21:30",
          "post_modified_gmt": "2022-03-31 02:21:30",
          "post_content_filtered": "",
          "post_parent": 856,
          "guid": "https://api.cannabis.ca.gov/2022/03/28/dcc-events/",
          "menu_order": 37,
          "post_type": "nav_menu_item",
          "post_mime_type": "",
          "comment_count": "0",
          "filter": "raw",
          "db_id": 9920,
          "menu_item_parent": "9921",
          "object_id": "7800",
          "object": "page",
          "type": "post_type",
          "type_label": "Page",
          "url": "https://api.cannabis.ca.gov/about-us/dcc-events/",
          "title": "DCC events",
          "target": "",
          "attr_title": "",
          "description": "",
          "classes": [
            ""
          ],
          "xfn": "",
          "slug": "dcc-events"
        },
        {
          "ID": 9910,
          "post_author": "1",
          "post_date": "2022-03-30 19:21:30",
          "post_date_gmt": "2022-03-29 05:23:29",
          "post_content": " ",
          "post_title": "",
          "post_excerpt": "",
          "post_status": "publish",
          "comment_status": "closed",
          "ping_status": "closed",
          "post_password": "",
          "post_name": "9910",
          "to_ping": "",
          "pinged": "",
          "post_modified": "2022-03-30 19:21:30",
          "post_modified_gmt": "2022-03-31 02:21:30",
          "post_content_filtered": "",
          "post_parent": 856,
          "guid": "https://api.cannabis.ca.gov/2022/03/28/9910/",
          "menu_order": 38,
          "post_type": "nav_menu_item",
          "post_mime_type": "",
          "comment_count": "0",
          "filter": "raw",
          "db_id": 9910,
          "menu_item_parent": "9921",
          "object_id": "700",
          "object": "page",
          "type": "post_type",
          "type_label": "Page",
          "url": "https://api.cannabis.ca.gov/about-us/public-awareness-campaigns/",
          "title": "Public awareness campaigns",
          "target": "",
          "attr_title": "",
          "description": "",
          "classes": [
            ""
          ],
          "xfn": "",
          "slug": "public-awareness-campaigns"
        },
        {
          "ID": 9929,
          "post_author": "1",
          "post_date": "2022-03-30 19:21:30",
          "post_date_gmt": "2022-03-29 05:23:30",
          "post_content": " ",
          "post_title": "",
          "post_excerpt": "",
          "post_status": "publish",
          "comment_status": "closed",
          "ping_status": "closed",
          "post_password": "",
          "post_name": "9929",
          "to_ping": "",
          "pinged": "",
          "post_modified": "2022-03-30 19:21:30",
          "post_modified_gmt": "2022-03-31 02:21:30",
          "post_content_filtered": "",
          "post_parent": 856,
          "guid": "https://api.cannabis.ca.gov/2022/03/28/9929/",
          "menu_order": 39,
          "post_type": "nav_menu_item",
          "post_mime_type": "",
          "comment_count": "0",
          "filter": "raw",
          "db_id": 9929,
          "menu_item_parent": "9921",
          "object_id": "694",
          "object": "page",
          "type": "post_type",
          "type_label": "Page",
          "url": "https://api.cannabis.ca.gov/about-us/scientific-research/",
          "title": "Scientific research",
          "target": "",
          "attr_title": "",
          "description": "",
          "classes": [
            ""
          ],
          "xfn": "",
          "slug": "scientific-research"
        },
        {
          "ID": 9928,
          "post_author": "1",
          "post_date": "2022-03-30 19:21:30",
          "post_date_gmt": "2022-03-29 05:23:30",
          "post_content": " ",
          "post_title": "",
          "post_excerpt": "",
          "post_status": "publish",
          "comment_status": "closed",
          "ping_status": "closed",
          "post_password": "",
          "post_name": "9928",
          "to_ping": "",
          "pinged": "",
          "post_modified": "2022-03-30 19:21:30",
          "post_modified_gmt": "2022-03-31 02:21:30",
          "post_content_filtered": "",
          "post_parent": 856,
          "guid": "https://api.cannabis.ca.gov/2022/03/28/9928/",
          "menu_order": 40,
          "post_type": "nav_menu_item",
          "post_mime_type": "",
          "comment_count": "0",
          "filter": "raw",
          "db_id": 9928,
          "menu_item_parent": "9921",
          "object_id": "703",
          "object": "page",
          "type": "post_type",
          "type_label": "Page",
          "url": "https://api.cannabis.ca.gov/about-us/grant-funding/",
          "title": "Grant funding",
          "target": "",
          "attr_title": "",
          "description": "",
          "classes": [
            ""
          ],
          "xfn": "",
          "slug": "grant-funding"
        },
        {
          "ID": 9930,
          "post_author": "1",
          "post_date": "2022-03-30 19:21:30",
          "post_date_gmt": "2022-03-29 05:23:30",
          "post_content": " ",
          "post_title": "",
          "post_excerpt": "",
          "post_status": "publish",
          "comment_status": "closed",
          "ping_status": "closed",
          "post_password": "",
          "post_name": "9930",
          "to_ping": "",
          "pinged": "",
          "post_modified": "2022-03-30 19:21:30",
          "post_modified_gmt": "2022-03-31 02:21:30",
          "post_content_filtered": "",
          "post_parent": 856,
          "guid": "https://api.cannabis.ca.gov/2022/03/28/9930/",
          "menu_order": 41,
          "post_type": "nav_menu_item",
          "post_mime_type": "",
          "comment_count": "0",
          "filter": "raw",
          "db_id": 9930,
          "menu_item_parent": "9921",
          "object_id": "9521",
          "object": "page",
          "type": "post_type",
          "type_label": "Page",
          "url": "https://api.cannabis.ca.gov/about-us/work-for-dcc/",
          "title": "Work for DCC",
          "target": "",
          "attr_title": "",
          "description": "",
          "classes": [
            ""
          ],
          "xfn": "",
          "slug": "work-for-dcc"
        },
        {
          "ID": 9886,
          "post_author": "1",
          "post_date": "2022-03-30 19:21:30",
          "post_date_gmt": "2022-03-29 05:22:05",
          "post_content": " ",
          "post_title": "",
          "post_excerpt": "",
          "post_status": "publish",
          "comment_status": "closed",
          "ping_status": "closed",
          "post_password": "",
          "post_name": "9886",
          "to_ping": "",
          "pinged": "",
          "post_modified": "2022-03-30 19:21:30",
          "post_modified_gmt": "2022-03-31 02:21:30",
          "post_content_filtered": "",
          "post_parent": 856,
          "guid": "https://api.cannabis.ca.gov/2022/03/28/",
          "menu_order": 42,
          "post_type": "nav_menu_item",
          "post_mime_type": "",
          "comment_count": "0",
          "filter": "raw",
          "db_id": 9886,
          "menu_item_parent": "9921",
          "object_id": "689",
          "object": "page",
          "type": "post_type",
          "type_label": "Page",
          "url": "https://api.cannabis.ca.gov/about-us/contact-us/",
          "title": "Contact us",
          "target": "",
          "attr_title": "",
          "description": "",
          "classes": [
            ""
          ],
          "xfn": "",
          "slug": "contact-us"
        }
      ]
    }
  ]
}