{
  "meta": {
    "created_date": "2021-12-07T00:43:07",
    "updated_date": "2021-12-07T00:43:13",
    "field_reference": "https://developer.wordpress.org/rest-api/reference/posts/",
    "api_version": "v2",
    "api_url": "https://live-drought-ca-gov.pantheonsite.io/wp-json/wp/v2/",
    "process": {
      "source_code": "https://github.com/cagov/wordpress-to-github",
      "source_data": "https://live-drought-ca-gov.pantheonsite.io",
      "deployment_target": "https://github.com/cagov/drought.ca.gov/tree/main"
    },
    "refresh_frequency": "as needed"
  },
  "data": {
    "id": 978,
    "date": "2021-12-06T16:43:07",
    "date_gmt": "2021-12-07T00:43:07",
    "guid": "https://live-drought-ca-gov.pantheonsite.io/?p=978",
    "modified": "2021-12-06T16:43:13",
    "modified_gmt": "2021-12-07T00:43:13",
    "slug": "dwr-awards-26-million-in-drought-support-to-small-communities",
    "status": "publish",
    "type": "post",
    "link": "https://live-drought-ca-gov.pantheonsite.io/dwr-awards-26-million-in-drought-support-to-small-communities/",
    "title": "DWR Awards $26 Million in Drought Support to Small Communities",
    "excerpt": "<p>The Department of Water Resources (DWR) announced $26 million in funding commitments to 11 communities through the Small Community Drought Relief program, created by the Budget Act of 2021.</p>\n",
    "author": "Peggy Gartin",
    "featured_media": 0,
    "comment_status": "closed",
    "ping_status": "closed",
    "sticky": false,
    "template": "",
    "format": "link",
    "meta": {
      "custom_post_link": "https://water.ca.gov/News/News-Releases/2021/Dec-21/Small-Community-Grants-December",
      "custom_post_date": "2021-12-06",
      "custom_post_location": ""
    },
    "categories": [
      "News"
    ],
    "tags": [],
    "design_system_fields": {
      "template": "post"
    },
    "og_meta": {
      "editor": {
        "platform": "WordPress",
        "plugin": "autodescription",
        "plugin_name": "The SEO Framework",
        "plugin_version": "4.1.5.1",
        "editor_url": "https://live-drought-ca-gov.pantheonsite.io"
      },
      "site_name": "California drought action",
      "site_description": "Learn more about current conditions, the state’s response and informational resources available to the public.",
      "site_url": "https://live-drought-ca-gov.pantheonsite.io",
      "canonical_url": "https://live-drought-ca-gov.pantheonsite.io/dwr-awards-26-million-in-drought-support-to-small-communities/",
      "page_title": "DWR Awards $26 Million in Drought Support to Small Communities",
      "page_description": "Learn more about current conditions, the state’s response and informational resources available to the public.",
      "page_social_image_url": "https://live-drought-ca-gov.pantheonsite.io/wp-content/uploads/2021/07/cropped-2021_06_23_FL_0494_Folsom_Lake.jpg",
      "page_social_image_width": 1200,
      "page_social_image_height": 630,
      "page_social_image_alt": "",
      "meta_title": "DWR Awards $26 Million in Drought Support to Small Communities",
      "meta_description": "Learn more about current conditions, the state’s response and informational resources available to the public.",
      "meta_canonical_url": "https://live-drought-ca-gov.pantheonsite.io/dwr-awards-26-million-in-drought-support-to-small-communities/",
      "open_graph_title": "DWR Awards $26 Million in Drought Support to Small Communities",
      "open_graph_description": "Learn more about current conditions, the state’s response and informational resources available to the public.",
      "twitter_title": "DWR Awards $26 Million in Drought Support to Small Communities",
      "twitter_description": "Learn more about current conditions, the state’s response and informational resources available to the public."
    },
    "headless_categories": [
      {
        "term_id": 7,
        "name": "News",
        "slug": "news",
        "term_group": 0,
        "term_taxonomy_id": 7,
        "taxonomy": "category",
        "description": "",
        "parent": 0,
        "filter": "raw",
        "cat_ID": 7,
        "category_description": "",
        "cat_name": "News",
        "category_nicename": "news",
        "category_parent": 0
      }
    ],
    "headless_tags": [],
    "headless_publishing": [],
    "headless_preview": [],
    "custom_post_date": "2021-12-06",
    "wordpress_url": "https://live-drought-ca-gov.pantheonsite.io/dwr-awards-26-million-in-drought-support-to-small-communities/"
  }
}