{
  "meta": {
    "created_date": "2018-04-06T17:58:00",
    "updated_date": "2021-06-14T19:16:46",
    "api_version": "v2",
    "api_url": "https://dev-cagov-dcc.pantheonsite.io/wp-json/wp/v2/",
    "process": {
      "source_code": "https://github.com/cagov/cron",
      "source_data": "https://dev-cagov-dcc.pantheonsite.io",
      "deployment_target": "https://github.com/cagov/cannabis.ca.gov/tree/main/wordpress"
    },
    "refresh_frequency": "as needed"
  },
  "data": {
    "id": 6260,
    "slug": "cdfa-and-cdph-temporary-license-extension-update",
    "title": "CDFA and CDPH Provide Temporary License Extension Update",
    "author": "Department of Cannabis Control",
    "date": "2018-04-06T17:58:00",
    "modified": "2021-06-14T19:16:46",
    "date_gmt": "2018-04-06T17:58:00",
    "modified_gmt": "2021-06-14T19:16:46",
    "wordpress_url": "https://dev-cagov-dcc.pantheonsite.io/2018/04/06/cdfa-and-cdph-temporary-license-extension-update/",
    "file_path_html": "posts/cdfa-and-cdph-temporary-license-extension-update.html",
    "file_path_json": "posts/cdfa-and-cdph-temporary-license-extension-update.json",
    "categories": [
      "Announcement"
    ],
    "tags": [
      "CalCannabis Cultivation Licensing",
      null,
      null,
      null,
      null,
      null,
      null,
      null,
      null
    ],
    "excerpt": "<p>The California Department of Food and Agriculture (CDFA) and the California Department of Public Health (CDPH) are in the process of sending notifications to holders of temporary cannabis licenses that are due to expire in early May 2018.</p>\n"
  }
}