{
  "meta": {
    "created_date": "2017-12-11T20:41:00",
    "updated_date": "2021-06-14T19:17:00",
    "foo": 1,
    "api_version": "v2",
    "api_url": "https://dev-cagov-dcc.pantheonsite.io/wp-json/wp/v2/",
    "process": {
      "source_code": "https://github.com/cagov/cron",
      "source_data": "https://dev-cagov-dcc.pantheonsite.io",
      "deployment_target": "https://github.com/cagov/cannabis.ca.gov/tree/main"
    },
    "refresh_frequency": "as needed"
  },
  "data": {
    "id": 6056,
    "slug": "secretary-of-state-alex-padilla-launches-cannabizfile-online-cannabis-business-portal",
    "title": "Secretary of State Alex Padilla Launches Cannabizfile Online Cannabis Business Portal, Releases PSA Featuring Actor Cheech Marin",
    "author": "Department of Cannabis Control",
    "date": "2017-12-11T20:41:00",
    "modified": "2021-06-14T19:17:00",
    "date_gmt": "2017-12-11T20:41:00",
    "modified_gmt": "2021-06-14T19:17:00",
    "meta": {
      "_et_pb_use_builder": "",
      "_et_pb_old_content": "",
      "_et_gb_content_width": ""
    },
    "template": "/code/wp-content/plugins/ca-design-system-gutenberg-blocks/includes/templates/template-single-press-release.php",
    "wordpress_url": "https://dev-cagov-dcc.pantheonsite.io/2017/12/11/secretary-of-state-alex-padilla-launches-cannabizfile-online-cannabis-business-portal/",
    "excerpt": "<p>SACRAMENTO &#8211; Secretary of State Alex Padilla announced today the launch of cannabizfile, a new online portal with useful information about cannabis-related business filings with the Secretary of State’s office.</p>\n",
    "categories": [
      "Press Releases"
    ],
    "tags": []
  }
}